uaaronium/__init__.py
uaaronium/arithmetic.py
uaaronium/differentiation.py
uaaronium/golden.py
uaaronium/iterative.py
uaaronium/logs_phi.py
uaaronium/logs_phi_bridge.py
uaaronium/number_systems.py
uaaronium/partial_diff.py
uaaronium/physics.py
uaaronium/roots.py
uaaronium/series_tools.py
uaaronium/taylor_engine.py
uaaronium-1.2.0.dist-info/METADATA
uaaronium-1.2.0.dist-info/WHEEL
uaaronium-1.2.0.dist-info/top_level.txt
uaaronium-1.2.0.dist-info/RECORD
