Metadata-Version: 2.4
Name: uaaronium
Version: 1.2.0
Summary: Uaaronium mathematics engine based on Aaron Craig Sinanan's book.
Author: Aaron Craig Sinanan
License: MIT
Project-URL: Homepage, https://github.com/aaronrah-ai
Requires-Python: >=3.8
Requires-Dist: sympy
Requires-Dist: numpy
